{
  "settings": {
    "teams": "data/iem_cologne_2026_stage1_teams.csv",
    "locked_results": "",
    "snapshot": "",
    "model_json": "reports/models/stage1_catboost_pairwise.json",
    "model": "catboost",
    "model_target": "advanced",
    "feature_snapshot": "data/snapshots/iem_cologne_major_2026_stage1_factor_weights_trained_2026-05-23.csv",
    "score_column": "feature_score",
    "stage_name": "Stage 1",
    "advance_label": "晋级",
    "simulations": 10000,
    "seed": 42,
    "scale": 120.0,
    "effective_scale": 150.0,
    "bo1_shrink": 0.7,
    "effective_bo1_shrink": 0.55,
    "bo3_shrink": 1.0,
    "effective_bo3_shrink": 0.9,
    "veto_weight": 1.0,
    "calibration_json": "reports/stage1_factor_veto_calibration.json",
    "all_bo3": false,
    "map_stats": "data/bo3/bo3_stage1_last4months_map_stats_complete_2026-05-25.csv",
    "map_pool": "Ancient, Anubis, Dust2, Inferno, Mirage, Nuke, Overpass",
    "veto_policy": "contextual-bandit",
    "bandit_policy_json": "reports/models/bo3_two_layer_veto_bandit_policy_2026-05-25.json",
    "catboost_metadata": {
      "model_path": "reports/models/stage1_catboost_pairwise.cbm",
      "stage1_training_mode": "fallback_major_pairwise",
      "stage2_training_mode": "austin_budapest_major_calibration_weighted_pairwise",
      "example_count": 424
    },
    "pass_threshold": 5,
    "three_zero_picks": 2,
    "zero_three_picks": 2,
    "advance_picks": 6
  },
  "probabilities": [
    {
      "team": "HEROIC",
      "seed": "3",
      "score": "247.1",
      "p_3_0": "38.3%",
      "p_3_1": "34.0%",
      "p_3_2": "21.3%",
      "p_advance": "93.6%",
      "p_2_3": "3.3%",
      "p_1_3": "2.5%",
      "p_0_3": "0.7%",
      "most_common_record": "3-0"
    },
    {
      "team": "B8",
      "seed": "2",
      "score": "245.1",
      "p_3_0": "34.5%",
      "p_3_1": "34.3%",
      "p_3_2": "23.7%",
      "p_advance": "92.6%",
      "p_2_3": "3.7%",
      "p_1_3": "3.0%",
      "p_0_3": "0.7%",
      "most_common_record": "3-0"
    },
    {
      "team": "BetBoom",
      "seed": "4",
      "score": "213.0",
      "p_3_0": "35.6%",
      "p_3_1": "34.1%",
      "p_3_2": "21.9%",
      "p_advance": "91.7%",
      "p_2_3": "4.3%",
      "p_1_3": "3.2%",
      "p_0_3": "0.8%",
      "most_common_record": "3-0"
    },
    {
      "team": "M80",
      "seed": "6",
      "score": "192.9",
      "p_3_0": "31.7%",
      "p_3_1": "36.6%",
      "p_3_2": "22.8%",
      "p_advance": "91.1%",
      "p_2_3": "4.2%",
      "p_1_3": "3.6%",
      "p_0_3": "1.1%",
      "most_common_record": "3-1"
    },
    {
      "team": "FlyQuest",
      "seed": "16",
      "score": "49.1",
      "p_3_0": "10.9%",
      "p_3_1": "24.8%",
      "p_3_2": "31.9%",
      "p_advance": "67.6%",
      "p_2_3": "15.9%",
      "p_1_3": "11.6%",
      "p_0_3": "4.9%",
      "most_common_record": "3-2"
    },
    {
      "team": "TYLOO",
      "seed": "10",
      "score": "18.2",
      "p_3_0": "7.5%",
      "p_3_1": "23.2%",
      "p_3_2": "31.2%",
      "p_advance": "61.8%",
      "p_2_3": "16.8%",
      "p_1_3": "14.4%",
      "p_0_3": "7.1%",
      "most_common_record": "3-2"
    },
    {
      "team": "BIG",
      "seed": "5",
      "score": "-16.9",
      "p_3_0": "11.1%",
      "p_3_1": "24.1%",
      "p_3_2": "25.6%",
      "p_advance": "60.8%",
      "p_2_3": "20.4%",
      "p_1_3": "13.9%",
      "p_0_3": "4.9%",
      "most_common_record": "3-2"
    },
    {
      "team": "SINNERS",
      "seed": "8",
      "score": "-40.4",
      "p_3_0": "6.8%",
      "p_3_1": "19.0%",
      "p_3_2": "26.9%",
      "p_advance": "52.7%",
      "p_2_3": "20.8%",
      "p_1_3": "17.7%",
      "p_0_3": "8.9%",
      "most_common_record": "3-2"
    },
    {
      "team": "MIBR",
      "seed": "7",
      "score": "-92.9",
      "p_3_0": "6.6%",
      "p_3_1": "16.6%",
      "p_3_2": "19.8%",
      "p_advance": "43.0%",
      "p_2_3": "26.8%",
      "p_1_3": "21.4%",
      "p_0_3": "8.8%",
      "most_common_record": "2-3"
    },
    {
      "team": "NRG",
      "seed": "9",
      "score": "-119.3",
      "p_3_0": "3.7%",
      "p_3_1": "10.4%",
      "p_3_2": "13.4%",
      "p_advance": "27.5%",
      "p_2_3": "30.5%",
      "p_1_3": "28.3%",
      "p_0_3": "13.7%",
      "most_common_record": "2-3"
    },
    {
      "team": "Sharks",
      "seed": "11",
      "score": "-118.8",
      "p_3_0": "2.4%",
      "p_3_1": "9.3%",
      "p_3_2": "13.2%",
      "p_advance": "25.0%",
      "p_2_3": "23.9%",
      "p_1_3": "28.8%",
      "p_0_3": "22.4%",
      "most_common_record": "1-3"
    },
    {
      "team": "Gaimin Gladiators",
      "seed": "12",
      "score": "-140.8",
      "p_3_0": "1.9%",
      "p_3_1": "8.2%",
      "p_3_2": "11.8%",
      "p_advance": "21.8%",
      "p_2_3": "24.7%",
      "p_1_3": "30.7%",
      "p_0_3": "22.8%",
      "most_common_record": "1-3"
    },
    {
      "team": "Liquid",
      "seed": "13",
      "score": "-144.5",
      "p_3_0": "2.5%",
      "p_3_1": "7.7%",
      "p_3_2": "11.4%",
      "p_advance": "21.6%",
      "p_2_3": "25.8%",
      "p_1_3": "29.6%",
      "p_0_3": "23.0%",
      "most_common_record": "1-3"
    },
    {
      "team": "GamerLegion",
      "seed": "1",
      "score": "-179.9",
      "p_3_0": "3.3%",
      "p_3_1": "7.7%",
      "p_3_2": "10.3%",
      "p_advance": "21.3%",
      "p_2_3": "31.6%",
      "p_1_3": "29.3%",
      "p_0_3": "17.8%",
      "most_common_record": "2-3"
    },
    {
      "team": "THUNDER dOWNUNDER",
      "seed": "15",
      "score": "-156.7",
      "p_3_0": "2.5%",
      "p_3_1": "7.1%",
      "p_3_2": "10.7%",
      "p_advance": "20.3%",
      "p_2_3": "26.9%",
      "p_1_3": "30.3%",
      "p_0_3": "22.4%",
      "most_common_record": "1-3"
    },
    {
      "team": "Lynn Vision",
      "seed": "14",
      "score": "-239.1",
      "p_3_0": "0.8%",
      "p_3_1": "3.0%",
      "p_3_2": "4.0%",
      "p_advance": "7.8%",
      "p_2_3": "20.6%",
      "p_1_3": "31.5%",
      "p_0_3": "40.1%",
      "most_common_record": "0-3"
    }
  ],
  "pickem_card": {
    "three_zero": [
      "B8",
      "BIG"
    ],
    "zero_three": [
      "Lynn Vision",
      "THUNDER dOWNUNDER"
    ],
    "advance": [
      "HEROIC",
      "BetBoom",
      "M80",
      "FlyQuest",
      "TYLOO",
      "SINNERS"
    ],
    "pass_probability": 0.854,
    "expected_correct": 5.6658
  }
}